accessPolygon/__init__.py
accessPolygon/access.py
accessPolygon/setup.py
accessPolygon-0.1.0.dist-info/LICENSE
accessPolygon-0.1.0.dist-info/METADATA
accessPolygon-0.1.0.dist-info/WHEEL
accessPolygon-0.1.0.dist-info/top_level.txt
accessPolygon-0.1.0.dist-info/RECORD
